MANIFEST.in
README.rst
setup.cfg
setup.py
python_slick_reporting.egg-info/PKG-INFO
python_slick_reporting.egg-info/SOURCES.txt
python_slick_reporting.egg-info/dependency_links.txt
python_slick_reporting.egg-info/requires.txt
python_slick_reporting.egg-info/top_level.txt
slick_reporting/__init__.py
slick_reporting/app_settings.py
slick_reporting/apps.py
slick_reporting/decorators.py
slick_reporting/fields.py
slick_reporting/form_factory.py
slick_reporting/forms.py
slick_reporting/generator.py
slick_reporting/helpers.py
slick_reporting/registry.py
slick_reporting/views.py
slick_reporting/templatetags/__init__.py
slick_reporting/templatetags/slick_reporting_tags.py
tests/__init__.py
tests/models.py
tests/report_generators.py
tests/test_generator.py
tests/test_settings.py
tests/tests.py
tests/urls.py
tests/views.py