Metadata-Version: 2.1
Name: python-slick-reporting
Version: 0.1.4
Summary: A one-stop report adn analytics generation and computation with batteries included
Home-page: https://github.com/ra-systems/django-slick-reporting
Author: Ra Systems
Author-email: ramez@rasystems.io
License: UNKNOWN
Project-URL: Travis CI, https://travis-ci.org/ra-systems/RA/
Project-URL: Documentation, https://ra-framework.readthedocs.io/en/latest/
Project-URL: Source, https://github.com/ra-systems/django-slick-reporting
Platform: UNKNOWN
Classifier: Environment :: Web Environment
Classifier: Framework :: Django
Classifier: Framework :: Django :: 2.2
Classifier: Framework :: Django :: 3.0
Classifier: Intended Audience :: Developers
Classifier: Development Status :: 3 - Alpha
Classifier: License :: OSI Approved :: BSD License
Classifier: Natural Language :: English
Classifier: Operating System :: MacOS :: MacOS X
Classifier: Operating System :: POSIX
Classifier: Operating System :: POSIX :: BSD
Classifier: Operating System :: POSIX :: Linux
Classifier: Operating System :: Microsoft :: Windows
Classifier: Programming Language :: Python
Classifier: Programming Language :: Python :: 3
Classifier: Programming Language :: Python :: 3 :: Only
Classifier: Programming Language :: Python :: 3.6
Classifier: Programming Language :: Python :: 3.7
Classifier: Programming Language :: Python :: 3.8
Classifier: Topic :: Internet :: WWW/HTTP
Classifier: Topic :: Internet :: WWW/HTTP :: Dynamic Content
Requires-Python: >=3.6
